Workbook

Sheet README
A1: CloudTask Pro — Churn & Unit Economics Analysis
A2: Excel companion workbook. The primary analysis lives in SQL (sql/) and the Power BI model design (powerbi/) — this workbook mirrors the same numbers for quick review, sanity-checking, and offline sharing.
A4: Tabs
A5: Subscriptions — Raw customer-level data, plus calculated helper columns (Is Churned, Is Active, Lifespan Months, Is At Risk) used by every formula in this workbook.
A6: Monthly Revenue — Raw monthly company summary, as delivered.
A7: Churn Summary — Churn rate by plan, billing cycle, acquisition channel, and company size — all live formulas (COUNTIFS/SUMIFS) against the Subscriptions tab.
A8: Churn Reasons — Top churn reasons overall and by plan.
A9: Unit Economics — Average CLV by plan vs. blended CAC, and the resulting CLV:CAC ratio.
A10: At-Risk Customers — Feature usage / NPS vs. churn relationship, the at-risk threshold definition, and the current at-risk customer list.
A12: Conventions
A13: Blue text on yellow fill — an assumption or input cell — the snapshot date and the at-risk threshold values.
A14: Black text — a live formula, not a typed-in result — every summary number recalculates if the raw data changes.

Sheet Subscriptions
A1: customer_id | B1: plan | C1: billing_cycle | D1: industry | E1: company_size | F1: seats | G1: monthly_revenue | H1: acquisition_channel | I1: region | J1: signup_date | K1: churned | L1: churn_date | M1: churn_reason | N1: support_tickets_12mo | O1: nps_score | P1: feature_usage_pct | Q1: upgraded | R1: Is Churned | S1: Is Active | T1: Lifespan Months | U1: Is At Risk
A2: CUST-0001 | B2: Professional | C2: Monthly | D2: Retail | E2: 51-200 | F2: 64 | G2: 825.55 | H2: Organic Search | I2: North America | J2: 44739 | K2: Yes | L2: 45356 | M2: Price Too High | N2: 13 | O2: 3 | P2: 15 | Q2: No | R2: =IF(K2="Yes",1,0) | S2: =IF(K2="No",1,0) | T2: =ROUND((IF(L2="",'Subscriptions'!$T$2,L2)-J2)/30.44,1) | U2: =IF(AND(P2<'Subscriptions'!$T$4,O2<='Subscriptions'!$T$5),1,0)
A3: CUST-0002 | B3: Professional | C3: Annual | D3: Retail | E3: 51-200 | F3: 35 | G3: 409.62 | H3: Direct Sales | I3: North America | J3: 45004 | K3: No | N3: 1 | O3: 3 | P3: 52 | Q3: Yes | R3: =IF(K3="Yes",1,0) | S3: =IF(K3="No",1,0) | T3: =ROUND((IF(L3="",'Subscriptions'!$T$2,L3)-J3)/30.44,1) | U3: =IF(AND(P3<'Subscriptions'!$T$4,O3<='Subscriptions'!$T$5),1,0)
A4: CUST-0003 | B4: Starter | C4: Annual | D4: Finance | E4: 500+ | F4: 266 | G4: 1004.49 | H4: Partner | I4: North America | J4: 45584 | K4: Yes | L4: 45760 | M4: Price Too High | N4: 10 | O4: 4 | P4: 31 | Q4: No | R4: =IF(K4="Yes",1,0) | S4: =IF(K4="No",1,0) | T4: =ROUND((IF(L4="",'Subscriptions'!$T$2,L4)-J4)/30.44,1) | U4: =IF(AND(P4<'Subscriptions'!$T$4,O4<='Subscriptions'!$T$5),1,0)
A5: CUST-0004 | B5: Business | C5: Annual | D5: Real Estate | E5: 11-50 | F5: 34 | G5: 1006.44 | H5: Partner | I5: Europe | J5: 44933 | K5: No | N5: 3 | O5: 7 | P5: 58 | Q5: No | R5: =IF(K5="Yes",1,0) | S5: =IF(K5="No",1,0) | T5: =ROUND((IF(L5="",'Subscriptions'!$T$2,L5)-J5)/30.44,1) | U5: =IF(AND(P5<'Subscriptions'!$T$4,O5<='Subscriptions'!$T$5),1,0)
A6: CUST-0005 | B6: Starter | C6: Annual | D6: Manufacturing | E6: 51-200 | F6: 48 | G6: 198.43 | H6: Direct Sales | I6: North America | J6: 45923 | K6: No | N6: 3 | O6: 7 | P6: 59 | Q6: No | R6: =IF(K6="Yes",1,0) | S6: =IF(K6="No",1,0) | T6: =ROUND((IF(L6="",'Subscriptions'!$T$2,L6)-J6)/30.44,1) | U6: =IF(AND(P6<'Subscriptions'!$T$4,O6<='Subscriptions'!$T$5),1,0)
A7: CUST-0006 | B7: Business | C7: Annual | D7: Technology | E7: 1-10 | F7: 3 | G7: 219.9 | H7: Referral | I7: North America | J7: 45197 | K7: No | N7: 12 | O7: 3 | P7: 48 | Q7: No | R7: =IF(K7="Yes",1,0) | S7: =IF(K7="No",1,0) | T7: =ROUND((IF(L7="",'Subscriptions'!$T$2,L7)-J7)/30.44,1) | U7: =IF(AND(P7<'Subscriptions'!$T$4,O7<='Subscriptions'!$T$5),1,0)
A8: CUST-0007 | B8: Starter | C8: Monthly | D8: Finance | E8: 201-500 | F8: 121 | G8: 551 | H8: Partner | I8: Europe | J8: 45358 | K8: Yes | L8: 45755 | M8: Poor Support | N8: 0 | O8: 2 | P8: 14 | Q8: No | R8: =IF(K8="Yes",1,0) | S8: =IF(K8="No",1,0) | T8: =ROUND((IF(L8="",'Subscriptions'!$T$2,L8)-J8)/30.44,1) | U8: =IF(AND(P8<'Subscriptions'!$T$4,O8<='Subscriptions'!$T$5),1,0)
A9: CUST-0008 | B9: Starter | C9: Monthly | D9: Technology | E9: 51-200 | F9: 48 | G9: 233.45 | H9: Referral | I9: Europe | J9: 45755 | K9: Yes | L9: 45816 | M9: Price Too High | N9: 10 | O9: 2 | P9: 28 | Q9: No | R9: =IF(K9="Yes",1,0) | S9: =IF(K9="No",1,0) | T9: =ROUND((IF(L9="",'Subscriptions'!$T$2,L9)-J9)/30.44,1) | U9: =IF(AND(P9<'Subscriptions'!$T$4,O9<='Subscriptions'!$T$5),1,0)
A10: CUST-0009 | B10: Starter | C10: Monthly | D10: Media | E10: 1-10 | F10: 3 | G10: 37.7 | H10: Partner | I10: North America | J10: 44948 | K10: Yes | L10: 45037 | M10: Switched Competitor | N10: 5 | O10: 6 | P10: 15 | Q10: No | R10: =IF(K10="Yes",1,0) | S10: =IF(K10="No",1,0) | T10: =ROUND((IF(L10="",'Subscriptions'!$T$2,L10)-J10)/30.44,1) | U10: =IF(AND(P10<'Subscriptions'!$T$4,O10<='Subscriptions'!$T$5),1,0)
A11: CUST-0010 | B11: Business | C11: Monthly | D11: Healthcare | E11: 51-200 | F11: 80 | G11: 2557.15 | H11: Partner | I11: North America | J11: 44739 | K11: Yes | L11: 45261 | M11: Budget Cuts | N11: 3 | O11: 4 | P11: 48 | Q11: No | R11: =IF(K11="Yes",1,0) | S11: =IF(K11="No",1,0) | T11: =ROUND((IF(L11="",'Subscriptions'!$T$2,L11)-J11)/30.44,1) | U11: =IF(AND(P11<'Subscriptions'!$T$4,O11<='Subscriptions'!$T$5),1,0)
A12: CUST-0011 | B12: Business | C12: Annual | D12: Healthcare | E12: 201-500 | F12: 77 | G12: 2097.46 | H12: Organic Search | I12: Asia Pacific | J12: 44902 | K12: Yes | L12: 45091 | M12: Company Closed | N12: 9 | O12: 1 | P12: 37 | Q12: No | R12: =IF(K12="Yes",1,0) | S12: =IF(K12="No",1,0) | T12: =ROUND((IF(L12="",'Subscriptions'!$T$2,L12)-J12)/30.44,1) | U12: =IF(AND(P12<'Subscriptions'!$T$4,O12<='Subscriptions'!$T$5),1,0)
A13: CUST-0012 | B13: Business | C13: Annual | D13: Technology | E13: 11-50 | F13: 30 | G13: 904.95 | H13: Referral | I13: North America | J13: 45247 | K13: No | N13: 4 | O13: 1 | P13: 47 | Q13: Yes | R13: =IF(K13="Yes",1,0) | S13: =IF(K13="No",1,0) | T13: =ROUND((IF(L13="",'Subscriptions'!$T$2,L13)-J13)/30.44,1) | U13: =IF(AND(P13<'Subscriptions'!$T$4,O13<='Subscriptions'!$T$5),1,0)
A14: CUST-0013 | B14: Business | C14: Monthly | D14: Finance | E14: 1-10 | F14: 4 | G14: 288.55 | H14: Referral | I14: Europe | J14: 45475 | K14: No | N14: 10 | O14: 9 | P14: 84 | Q14: Yes | R14: =IF(K14="Yes",1,0) | S14: =IF(K14="No",1,0) | T14: =ROUND((IF(L14="",'Subscriptions'!$T$2,L14)-J14)/30.44,1) | U14: =IF(AND(P14<'Subscriptions'!$T$4,O14<='Subscriptions'!$T$5),1,0)
A15: CUST-0014 | B15: Starter | C15: Monthly | D15: Retail | E15: 51-200 | F15: 56 | G15: 268.25 | H15: Paid Ads | I15: Europe | J15: 44710 | K15: Yes | L15: 44831 | M15: Poor Support | N15: 1 | O15: 2 | P15: 21 | Q15: No | R15: =IF(K15="Yes",1,0) | S15: =IF(K15="No",1,0) | T15: =ROUND((IF(L15="",'Subscriptions'!$T$2,L15)-J15)/30.44,1) | U15: =IF(AND(P15<'Subscriptions'!$T$4,O15<='Subscriptions'!$T$5),1,0)
A16: CUST-0015 | B16: Starter | C16: Monthly | D16: Education | E16: 1-10 | F16: 6 | G16: 50.75 | H16: Referral | I16: North America | J16: 45308 | K16: Yes | L16: 45428 | M16: No Longer Needed | N16: 7 | O16: 3 | P16: 25 | Q16: No | R16: =IF(K16="Yes",1,0) | S16: =IF(K16="No",1,0) | T16: =ROUND((IF(L16="",'Subscriptions'!$T$2,L16)-J16)/30.44,1) | U16: =IF(AND(P16<'Subscriptions'!$T$4,O16<='Subscriptions'!$T$5),1,0)
A17: CUST-0016 | B17: Starter | C17: Monthly | D17: Manufacturing | E17: 201-500 | F17: 52 | G17: 250.85 | H17: Organic Search | I17: North America | J17: 44713 | K17: Yes | L17: 44950 | M17: Budget Cuts | N17: 11 | O17: 4 | P17: 34 | Q17: No | R17: =IF(K17="Yes",1,0) | S17: =IF(K17="No",1,0) | T17: =ROUND((IF(L17="",'Subscriptions'!$T$2,L17)-J17)/30.44,1) | U17: =IF(AND(P17<'Subscriptions'!$T$4,O17<='Subscriptions'!$T$5),1,0)
A18: CUST-0017 | B18: Business | C18: Monthly | D18: Education | E18: 11-50 | F18: 34 | G18: 1184.05 | H18: Paid Ads | I18: North America | J18: 45649 | K18: Yes | L18: 45657 | M18: No Longer Needed | N18: 3 | O18: 3 | P18: 49 | Q18: No | R18: =IF(K18="Yes",1,0) | S18: =IF(K18="No",1,0) | T18: =ROUND((IF(L18="",'Subscriptions'!$T$2,L18)-J18)/30.44,1) | U18: =IF(AND(P18<'Subscriptions'!$T$4,O18<='Subscriptions'!$T$5),1,0)
A19: CUST-0018 | B19: Starter | C19: Monthly | D19: Media | E19: 51-200 | F19: 64 | G19: 303.05 | H19: Referral | I19: Europe | J19: 45098 | K19: Yes | L19: 45143 | M19: Company Closed | N19: 14 | O19: 3 | P19: 25 | Q19: No | R19: =IF(K19="Yes",1,0) | S19: =IF(K19="No",1,0) | T19: =ROUND((IF(L19="",'Subscriptions'!$T$2,L19)-J19)/30.44,1) | U19: =IF(AND(P19<'Subscriptions'!$T$4,O19<='Subscriptions'!$T$5),1,0)
A20: CUST-0019 | B20: Professional | C20: Annual | D20: Legal | E20: 500+ | F20: 67 | G20: 731.93 | H20: Partner | I20: Latin America | J20: 45377 | K20: Yes | L20: 45770 | M20: Company Closed | N20: 10 | O20: 2 | P20: 10 | Q20: No | R20: =IF(K20="Yes",1,0) | S20: =IF(K20="No",1,0) | T20: =ROUND((IF(L20="",'Subscriptions'!$T$2,L20)-J20)/30.44,1) | U20: =IF(AND(P20<'Subscriptions'!$T$4,O20<='Subscriptions'!$T$5),1,0)
A21: CUST-0020 | B21: Enterprise | C21: Annual | D21: Education | E21: 1-10 | F21: 7 | G21: 805.88 | H21: Organic Search | I21: Asia Pacific | J21: 45149 | K21: No | N21: 8 | O21: 4 | P21: 93 | Q21: No | R21: =IF(K21="Yes",1,0) | S21: =IF(K21="No",1,0) | T21: =ROUND((IF(L21="",'Subscriptions'!$T$2,L21)-J21)/30.44,1) | U21: =IF(AND(P21<'Subscriptions'!$T$4,O21<='Subscriptions'!$T$5),1,0)
A22: CUST-0021 | B22: Professional | C22: Annual | D22: Retail | E22: 51-200 | F22: 66 | G22: 721.86 | H22: Partner | I22: Europe | J22: 45253 | K22: Yes | L22: 45430 | M22: Price Too High | N22: 7 | O22: 2 | P22: 19 | Q22: No | R22: =IF(K22="Yes",1,0) | S22: =IF(K22="No",1,0) | T22: =ROUND((IF(L22="",'Subscriptions'!$T$2,L22)-J22)/30.44,1) | U22: =IF(AND(P22<'Subscriptions'!$T$4,O22<='Subscriptions'!$T$5),1,0)
A23: CUST-0022 | B23: Business | C23: Annual | D23: Education | E23: 1-10 | F23: 6 | G23: 296.01 | H23: Referral | I23: Europe | J23: 44744 | K23: No | N23: 5 | O23: 7 | P23: 40 | Q23: No | R23: =IF(K23="Yes",1,0) | S23: =IF(K23="No",1,0) | T23: =ROUND((IF(L23="",'Subscriptions'!$T$2,L23)-J23)/30.44,1) | U23: =IF(AND(P23<'Subscriptions'!$T$4,O23<='Subscriptions'!$T$5),1,0)
A24: CUST-0023 | B24: Starter | C24: Monthly | D24: Healthcare | E24: 11-50 | F24: 25 | G24: 133.4 | H24: Paid Ads | I24: Europe | J24: 45339 | K24: Yes | L24: 45405 | M24: Company Closed | N24: 11 | O24: 1 | P24: 16 | Q24: No | R24: =IF(K24="Yes",1,0) | S24: =IF(K24="No",1,0) | T24: =ROUND((IF(L24="",'Subscriptions'!$T$2,L24)-J24)/30.44,1) | U24: =IF(AND(P24<'Subscriptions'!$T$4,O24<='Subscriptions'!$T$5),1,0)
A25: CUST-0024 | B25: Enterprise | C25: Annual | D25: Manufacturing | E25: 11-50 | F25: 14 | G25: 1251.24 | H25: Referral | I25: Europe | J25: 45799 | K25: No | N25: 11 | O25: 1 | P25: 85 | Q25: No | R25: =IF(K25="Yes",1,0) | S25: =IF(K25="No",1,0) | T25: =ROUND((IF(L25="",'Subscriptions'!$T$2,L25)-J25)/30.44,1) | U25: =IF(AND(P25<'Subscriptions'!$T$4,O25<='Subscriptions'!$T$5),1,0)
A26: CUST-0025 | B26: Starter | C26: Annual | D26: Retail | E26: 11-50 | F26: 7 | G26: 46.83 | H26: Referral | I26: North America | J26: 45451 | K26: No | N26: 1 | O26: 1 | P26: 42 | Q26: No | R26: =IF(K26="Yes",1,0) | S26: =IF(K26="No",1,0) | T26: =ROUND((IF(L26="",'Subscriptions'!$T$2,L26)-J26)/30.44,1) | U26: =IF(AND(P26<'Subscriptions'!$T$4,O26<='Subscriptions'!$T$5),1,0)
A27: CUST-0026 | B27: Enterprise | C27: Annual | D27: Media | E27: 1-10 | F27: 4 | G27: 615.02 | H27: Referral | I27: Europe | J27: 45863 | K27: No | N27: 2 | O27: 9 | P27: 73 | Q27: No | R27: =IF(K27="Yes",1,0) | S27: =IF(K27="No",1,0) | T27: =ROUND((IF(L27="",'Subscriptions'!$T$2,L27)-J27)/30.44,1) | U27: =IF(AND(P27<'Subscriptions'!$T$4,O27<='Subscriptions'!$T$5),1,0)
A28: CUST-0027 | B28: Starter | C28: Monthly | D28: Consulting | E28: 1-10 | F28: 1 | G28: 29 | H28: Partner | I28: Asia Pacific | J28: 45179 | K28: Yes | L28: 45771 | M28: Poor Support | N28: 8 | O28: 3 | P28: 10 | Q28: No | R28: =IF(K28="Yes",1,0) | S28: =IF(K28="No",1,0) | T28: =ROUND((IF(L28="",'Subscriptions'!$T$2,L28)-J28)/30.44,1) | U28: =IF(AND(P28<'Subscriptions'!$T$4,O28<='Subscriptions'!$T$5),1,0)
A29: CUST-0028 | B29: Professional | C29: Annual | D29: Technology | E29: 51-200 | F29: 35 | G29: 409.62 | H29: Organic Search | I29: Latin America | J29: 46020 | K29: No | N29: 8 | O29: 4 | P29: 53 | Q29: No | R29: =IF(K29="Yes",1,0) | S29: =IF(K29="No",1,0) | T29: =ROUND((IF(L29="",'Subscriptions'!$T$2,L29)-J29)/30.44,1) | U29: =IF(AND(P29<'Subscriptions'!$T$4,O29<='Subscriptions'!$T$5),1,0)
A30: CUST-0029 | B30: Starter | C30: Monthly | D30: Real Estate | E30: 11-50 | F30: 22 | G30: 120.35 | H30: Organic Search | I30: North America | J30: 44901 | K30: Yes | L30: 45153 | M30: Missing Features | N30: 4 | O30: 2 | P30: 17 | Q30: No | R30: =IF(K30="Yes",1,0) | S30: =IF(K30="No",1,0) | T30: =ROUND((IF(L30="",'Subscriptions'!$T$2,L30)-J30)/30.44,1) | U30: =IF(AND(P30<'Subscriptions'!$T$4,O30<='Subscriptions'!$T$5),1,0)
A31: CUST-0030 | B31: Business | C31: Annual | D31: Real Estate | E31: 500+ | F31: 230 | G31: 5979.45 | H31: Partner | I31: Europe | J31: 45234 | K31: No | N31: 9 | O31: 3 | P31: 76 | Q31: No | R31: =IF(K31="Yes",1,0) | S31: =IF(K31="No",1,0) | T31: =ROUND((IF(L31="",'Subscriptions'!$T$2,L31)-J31)/30.44,1) | U31: =IF(AND(P31<'Subscriptions'!$T$4,O31<='Subscriptions'!$T$5),1,0)
A32: CUST-0031 | B32: Business | C32: Annual | D32: Finance | E32: 500+ | F32: 174 | G32: 4558.59 | H32: Direct Sales | I32: Europe | J32: 45493 | K32: No | N32: 8 | O32: 7 | P32: 84 | Q32: No | R32: =IF(K32="Yes",1,0) | S32: =IF(K32="No",1,0) | T32: =ROUND((IF(L32="",'Subscriptions'!$T$2,L32)-J32)/30.44,1) | U32: =IF(AND(P32<'Subscriptions'!$T$4,O32<='Subscriptions'!$T$5),1,0)
A33: CUST-0032 | B33: Enterprise | C33: Annual | D33: Technology | E33: 1-10 | F33: 5 | G33: 678.64 | H33: Referral | I33: North America | J33: 45013 | K33: No | N33: 7 | O33: 8 | P33: 16 | Q33: No | R33: =IF(K33="Yes",1,0) | S33: =IF(K33="No",1,0) | T33: =ROUND((IF(L33="",'Subscriptions'!$T$2,L33)-J33)/30.44,1) | U33: =IF(AND(P33<'Subscriptions'!$T$4,O33<='Subscriptions'!$T$5),1,0)
A34: CUST-0033 | B34: Starter | C34: Annual | D34: Consulting | E34: 1-10 | F34: 6 | G34: 43.14 | H34: Organic Search | I34: Latin America | J34: 45431 | K34: Yes | L34: 45502 | M34: No Longer Needed | N34: 11 | O34: 3 | P34: 30 | Q34: No | R34: =IF(K34="Yes",1,0) | S34: =IF(K34="No",1,0) | T34: =ROUND((IF(L34="",'Subscriptions'!$T$2,L34)-J34)/30.44,1) | U34: =IF(AND(P34<'Subscriptions'!$T$4,O34<='Subscriptions'!$T$5),1,0)
A35: CUST-0034 | B35: Enterprise | C35: Annual | D35: Education | E35: 11-50 | F35: 35 | G35: 2587.32 | H35: Referral | I35: North America | J35: 45194 | K35: No | N35: 5 | O35: 8 | P35: 33 | Q35: Yes | R35: =IF(K35="Yes",1,0) | S35: =IF(K35="No",1,0) | T35: =ROUND((IF(L35="",'Subscriptions'!$T$2,L35)-J35)/30.44,1) | U35: =IF(AND(P35<'Subscriptions'!$T$4,O35<='Subscriptions'!$T$5),1,0)
A36: CUST-0035 | B36: Starter | C36: Monthly | D36: Manufacturing | E36: 51-200 | F36: 70 | G36: 329.15 | H36: Organic Search | I36: Latin America | J36: 44689 | K36: Yes | L36: 44766 | M36: Switched Competitor | N36: 0 | O36: 6 | P36: 30 | Q36: No | R36: =IF(K36="Yes",1,0) | S36: =IF(K36="No",1,0) | T36: =ROUND((IF(L36="",'Subscriptions'!$T$2,L36)-J36)/30.44,1) | U36: =IF(AND(P36<'Subscriptions'!$T$4,O36<='Subscriptions'!$T$5),1,0)
A37: CUST-0036 | B37: Professional | C37: Monthly | D37: Manufacturing | E37: 1-10 | F37: 7 | G37: 150.1 | H37: Referral | I37: Latin America | J37: 45038 | K37: Yes | L37: 45284 | M37: Company Closed | N37: 10 | O37: 6 | P37: 16 | Q37: No | R37: =IF(K37="Yes",1,0) | S37: =IF(K37="No",1,0) | T37: =ROUND((IF(L37="",'Subscriptions'!$T$2,L37)-J37)/30.44,1) | U37: =IF(AND(P37<'Subscriptions'!$T$4,O37<='Subscriptions'!$T$5),1,0)
A38: CUST-0037 | B38: Professional | C38: Monthly | D38: Technology | E38: 1-10 | F38: 2 | G38: 90.85 | H38: Direct Sales | I38: North America | J38: 45457 | K38: Yes | L38: 45604 | M38: No Longer Needed | N38: 11 | O38: 2 | P38: 34 | Q38: No | R38: =IF(K38="Yes",1,0) | S38: =IF(K38="No",1,0) | T38: =ROUND((IF(L38="",'Subscriptions'!$T$2,L38)-J38)/30.44,1) | U38: =IF(AND(P38<'Subscriptions'!$T$4,O38<='Subscriptions'!$T$5),1,0)
A39: CUST-0038 | B39: Professional | C39: Monthly | D39: Real Estate | E39: 1-10 | F39: 5 | G39: 126.4 | H39: Organic Search | I39: Europe | J39: 44718 | K39: Yes | L39: 44784 | M39: Budget Cuts | N39: 6 | O39: 1 | P39: 30 | Q39: No | R39: =IF(K39="Yes",1,0) | S39: =IF(K39="No",1,0) | T39: =ROUND((IF(L39="",'Subscriptions'!$T$2,L39)-J39)/30.44,1) | U39: =IF(AND(P39<'Subscriptions'!$T$4,O39<='Subscriptions'!$T$5),1,0)
A40: CUST-0039 | B40: Business | C40: Annual | D40: Retail | E40: 51-200 | F40: 30 | G40: 904.95 | H40: Organic Search | I40: Asia Pacific | J40: 45414 | K40: No | N40: 4 | O40: 9 | P40: 71 | Q40: Yes | R40: =IF(K40="Yes",1,0) | S40: =IF(K40="No",1,0) | T40: =ROUND((IF(L40="",'Subscriptions'!$T$2,L40)-J40)/30.44,1) | U40: =IF(AND(P40<'Subscriptions'!$T$4,O40<='Subscriptions'!$T$5),1,0)
A41: CUST-0040 | B41: Business | C41: Annual | D41: Media | E41: 11-50 | F41: 24 | G41: 752.72 | H41: Direct Sales | I41: Asia Pacific | J41: 45063 | K41: No | N41: 9 | O41: 2 | P41: 76 | Q41: No | R41: =IF(K41="Yes",1,0) | S41: =IF(K41="No",1,0) | T41: =ROUND((IF(L41="",'Subscriptions'!$T$2,L41)-J41)/30.44,1) | U41: =IF(AND(P41<'Subscriptions'!$T$4,O41<='Subscriptions'!$T$5),1,0)
A42: CUST-0041 | B42: Starter | C42: Monthly | D42: Education | E42: 51-200 | F42: 53 | G42: 255.2 | H42: Referral | I42: Asia Pacific | J42: 44916 | K42: Yes | L42: 45065 | M42: Poor Support | N42: 4 | O42: 5 | P42: 45 | Q42: No | R42: =IF(K42="Yes",1,0) | S42: =IF(K42="No",1,0) | T42: =ROUND((IF(L42="",'Subscriptions'!$T$2,L42)-J42)/30.44,1) | U42: =IF(AND(P42<'Subscriptions'!$T$4,O42<='Subscriptions'!$T$5),1,0)
A43: CUST-0042 | B43: Starter | C43: Monthly | D43: Real Estate | E43: 51-200 | F43: 34 | G43: 172.55 | H43: Partner | I43: Europe | J43: 45661 | K43: No | N43: 9 | O43: 2 | P43: 73 | Q43: No | R43: =IF(K43="Yes",1,0) | S43: =IF(K43="No",1,0) | T43: =ROUND((IF(L43="",'Subscriptions'!$T$2,L43)-J43)/30.44,1) | U43: =IF(AND(P43<'Subscriptions'!$T$4,O43<='Subscriptions'!$T$5),1,0)
A44: CUST-0043 | B44: Professional | C44: Annual | D44: Manufacturing | E44: 1-10 | F44: 2 | G44: 77.22 | H44: Paid Ads | I44: Europe | J44: 44612 | K44: No | N44: 9 | O44: 9 | P44: 20 | Q44: No | R44: =IF(K44="Yes",1,0) | S44: =IF(K44="No",1,0) | T44: =ROUND((IF(L44="",'Subscriptions'!$T$2,L44)-J44)/30.44,1) | U44: =IF(AND(P44<'Subscriptions'!$T$4,O44<='Subscriptions'!$T$5),1,0)
A45: CUST-0044 | B45: Professional | C45: Annual | D45: Legal | E45: 1-10 | F45: 2 | G45: 77.22 | H45: Social Media | I45: North America | J45: 44678 | K45: Yes | L45: 44775 | M45: Price Too High | N45: 7 | O45: 6 | P45: 20 | Q45: No | R45: =IF(K45="Yes",1,0) | S45: =IF(K45="No",1,0) | T45: =ROUND((IF(L45="",'Subscriptions'!$T$2,L45)-J45)/30.44,1) | U45: =IF(AND(P45<'Subscriptions'!$T$4,O45<='Subscriptions'!$T$5),1,0)
A46: CUST-0045 | B46: Starter | C46: Monthly | D46: Retail | E46: 11-50 | F46: 7 | G46: 55.1 | H46: Social Media | I46: Latin America | J46: 45910 | K46: No | N46: 12 | O46: 4 | P46: 67 | Q46: No | R46: =IF(K46="Yes",1,0) | S46: =IF(K46="No",1,0) | T46: =ROUND((IF(L46="",'Subscriptions'!$T$2,L46)-J46)/30.44,1) | U46: =IF(AND(P46<'Subscriptions'!$T$4,O46<='Subscriptions'!$T$5),1,0)
A47: CUST-0046 | B47: Professional | C47: Monthly | D47: Finance | E47: 1-10 | F47: 4 | G47: 114.55 | H47: Paid Ads | I47: North America | J47: 45114 | K47: Yes | L47: 45350 | M47: Missing Features | N47: 1 | O47: 6 | P47: 42 | Q47: No | R47: =IF(K47="Yes",1,0) | S47: =IF(K47="No",1,0) | T47: =ROUND((IF(L47="",'Subscriptions'!$T$2,L47)-J47)/30.44,1) | U47: =IF(AND(P47<'Subscriptions'!$T$4,O47<='Subscriptions'!$T$5),1,0)
A48: CUST-0047 | B48: Business | C48: Monthly | D48: Media | E48: 1-10 | F48: 5 | G48: 318.4 | H48: Partner | I48: North America | J48: 44943 | K48: Yes | L48: 45821 | M48: No Longer Needed | N48: 15 | O48: 4 | P48: 46 | Q48: No | R48: =IF(K48="Yes",1,0) | S48: =IF(K48="No",1,0) | T48: =ROUND((IF(L48="",'Subscriptions'!$T$2,L48)-J48)/30.44,1) | U48: =IF(AND(P48<'Subscriptions'!$T$4,O48<='Subscriptions'!$T$5),1,0)
A49: CUST-0048 | B49: Business | C49: Annual | D49: Education | E49: 1-10 | F49: 4 | G49: 245.27 | H49: Referral | I49: Europe | J49: 44669 | K49: Yes | L49: 44754 | M49: Budget Cuts | N49: 4 | O49: 5 | P49: 16 | Q49: No | R49: =IF(K49="Yes",1,0) | S49: =IF(K49="No",1,0) | T49: =ROUND((IF(L49="",'Subscriptions'!$T$2,L49)-J49)/30.44,1) | U49: =IF(AND(P49<'Subscriptions'!$T$4,O49<='Subscriptions'!$T$5),1,0)
A50: CUST-0049 | B50: Professional | C50: Monthly | D50: Real Estate | E50: 51-200 | F50: 36 | G50: 493.75 | H50: Partner | I50: Asia Pacific | J50: 44699 | K50: Yes | L50: 44800 | M50: Poor Support | N50: 1 | O50: 6 | P50: 26 | Q50: No | R50: =IF(K50="Yes",1,0) | S50: =IF(K50="No",1,0) | T50: =ROUND((IF(L50="",'Subscriptions'!$T$2,L50)-J50)/30.44,1) | U50: =IF(AND(P50<'Subscriptions'!$T$4,O50<='Subscriptions'!$T$5),1,0)
A51: CUST-0050 | B51: Starter | C51: Annual | D51: Healthcare | E51: 1-10 | F51: 7 | G51: 46.83 | H51: Organic Search | I51: North America | J51: 44734 | K51: Yes | L51: 45473 | M51: Price Too High | N51: 2 | O51: 3 | P51: 38 | Q51: No | R51: =IF(K51="Yes",1,0) | S51: =IF(K51="No",1,0) | T51: =ROUND((IF(L51="",'Subscriptions'!$T$2,L51)-J51)/30.44,1) | U51: =IF(AND(P51<'Subscriptions'!$T$4,O51<='Subscriptions'!$T$5),1,0)
A52: CUST-0051 | B52: Professional | C52: Monthly | D52: Consulting | E52: 51-200 | F52: 58 | G52: 754.45 | H52: Partner | I52: Europe | J52: 44922 | K52: Yes | L52: 45030 | M52: Price Too High | N52: 10 | O52: 3 | P52: 29 | Q52: No | R52: =IF(K52="Yes",1,0) | S52: =IF(K52="No",1,0) | T52: =ROUND((IF(L52="",'Subscriptions'!$T$2,L52)-J52)/30.44,1) | U52: =IF(AND(P52<'Subscriptions'!$T$4,O52<='Subscriptions'!$T$5),1,0)
A53: CUST-0052 | B53: Starter | C53: Monthly | D53: Healthcare | E53: 201-500 | F53: 138 | G53: 624.95 | H53: Referral | I53: North America | J53: 45732 | K53: Yes | L53: 45853 | M53: Budget Cuts | N53: 0 | O53: 1 | P53: 38 | Q53: No | R53: =IF(K53="Yes",1,0) | S53: =IF(K53="No",1,0) | T53: =ROUND((IF(L53="",'Subscriptions'!$T$2,L53)-J53)/30.44,1) | U53: =IF(AND(P53<'Subscriptions'!$T$4,O53<='Subscriptions'!$T$5),1,0)
A54: CUST-0053 | B54: Starter | C54: Monthly | D54: Manufacturing | E54: 1-10 | F54: 4 | G54: 42.05 | H54: Organic Search | I54: North America | J54: 45750 | K54: Yes | L54: 45842 | M54: Price Too High | N54: 1 | O54: 2 | P54: 43 | Q54: No | R54: =IF(K54="Yes",1,0) | S54: =IF(K54="No",1,0) | T54: =ROUND((IF(L54="",'Subscriptions'!$T$2,L54)-J54)/30.44,1) | U54: =IF(AND(P54<'Subscriptions'!$T$4,O54<='Subscriptions'!$T$5),1,0)
A55: CUST-0054 | B55: Professional | C55: Annual | D55: Healthcare | E55: 201-500 | F55: 82 | G55: 883.02 | H55: Social Media | I55: North America | J55: 45466 | K55: No | N55: 4 | O55: 8 | P55: 81 | Q55: No | R55: =IF(K55="Yes",1,0) | S55: =IF(K55="No",1,0) | T55: =ROUND((IF(L55="",'Subscriptions'!$T$2,L55)-J55)/30.44,1) | U55: =IF(AND(P55<'Subscriptions'!$T$4,O55<='Subscriptions'!$T$5),1,0)
A56: CUST-0055 | B56: Business | C56: Monthly | D56: Manufacturing | E56: 1-10 | F56: 7 | G56: 378.1 | H56: Organic Search | I56: North America | J56: 44664 | K56: Yes | L56: 45551 | M56: Missing Features | N56: 6 | O56: 2 | P56: 21 | Q56: No | R56: =IF(K56="Yes",1,0) | S56: =IF(K56="No",1,0) | T56: =ROUND((IF(L56="",'Subscriptions'!$T$2,L56)-J56)/30.44,1) | U56: =IF(AND(P56<'Subscriptions'!$T$4,O56<='Subscriptions'!$T$5),1,0)
A57: CUST-0056 | B57: Business | C57: Monthly | D57: Technology | E57: 11-50 | F57: 14 | G57: 587.05 | H57: Paid Ads | I57: North America | J57: 45649 | K57: Yes | L57: 45976 | M57: Missing Features | N57: 3 | O57: 2 | P57: 37 | Q57: No | R57: =IF(K57="Yes",1,0) | S57: =IF(K57="No",1,0) | T57: =ROUND((IF(L57="",'Subscriptions'!$T$2,L57)-J57)/30.44,1) | U57: =IF(AND(P57<'Subscriptions'!$T$4,O57<='Subscriptions'!$T$5),1,0)
A58: CUST-0057 | B58: Professional | C58: Annual | D58: Healthcare | E58: 11-50 | F58: 34 | G58: 399.54 | H58: Referral | I58: North America | J58: 45485 | K58: Yes | L58: 45874 | M58: No Longer Needed | N58: 1 | O58: 1 | P58: 10 | Q58: No | R58: =IF(K58="Yes",1,0) | S58: =IF(K58="No",1,0) | T58: =ROUND((IF(L58="",'Subscriptions'!$T$2,L58)-J58)/30.44,1) | U58: =IF(AND(P58<'Subscriptions'!$T$4,O58<='Subscriptions'!$T$5),1,0)
A59: CUST-0058 | B59: Starter | C59: Monthly | D59: Real Estate | E59: 201-500 | F59: 48 | G59: 233.45 | H59: Referral | I59: Europe | J59: 44814 | K59: Yes | L59: 45002 | M59: Price Too High | N59: 2 | O59: 1 | P59: 12 | Q59: No | R59: =IF(K59="Yes",1,0) | S59: =IF(K59="No",1,0) | T59: =ROUND((IF(L59="",'Subscriptions'!$T$2,L59)-J59)/30.44,1) | U59: =IF(AND(P59<'Subscriptions'!$T$4,O59<='Subscriptions'!$T$5),1,0)
A60: CUST-0059 | B60: Professional | C60: Annual | D60: Healthcare | E60: 11-50 | F60: 28 | G60: 339.11 | H60: Social Media | I60: North America | J60: 45290 | K60: Yes | L60: 45575 | M60: Missing Features | N60: 5 | O60: 1 | P60: 13 | Q60: No | R60: =IF(K60="Yes",1,0) | S60: =IF(K60="No",1,0) | T60: =ROUND((IF(L60="",'Subscriptions'!$T$2,L60)-J60)/30.44,1) | U60: =IF(AND(P60<'Subscriptions'!$T$4,O60<='Subscriptions'!$T$5),1,0)
A61: CUST-0060 | B61: Professional | C61: Monthly | D61: Finance | E61: 51-200 | F61: 59 | G61: 766.3 | H61: Partner | I61: Asia Pacific | J61: 45503 | K61: Yes | L61: 45542 | M61: Switched Competitor | N61: 12 | O61: 1 | P61: 45 | Q61: No | R61: =IF(K61="Yes",1,0) | S61: =IF(K61="No",1,0) | T61: =ROUND((IF(L61="",'Subscriptions'!$T$2,L61)-J61)/30.44,1) | U61: =IF(AND(P61<'Subscriptions'!$T$4,O61<='Subscriptions'!$T$5),1,0)
A62: CUST-0061 | B62: Business | C62: Monthly | D62: Legal | E62: 51-200 | F62: 53 | G62: 1751.2 | H62: Referral | I62: Europe | J62: 44645 | K62: Yes | L62: 45022 | M62: Switched Competitor | N62: 13 | O62: 5 | P62: 11 | Q62: No | R62: =IF(K62="Yes",1,0) | S62: =IF(K62="No",1,0) | T62: =ROUND((IF(L62="",'Subscriptions'!$T$2,L62)-J62)/30.44,1) | U62: =IF(AND(P62<'Subscriptions'!$T$4,O62<='Subscriptions'!$T$5),1,0)
A63: CUST-0062 | B63: Professional | C63: Monthly | D63: Finance | E63: 11-50 | F63: 21 | G63: 316 | H63: Paid Ads | I63: North America | J63: 44835 | K63: Yes | L63: 45395 | M63: Switched Competitor | N63: 1 | O63: 3 | P63: 16 | Q63: No | R63: =IF(K63="Yes",1,0) | S63: =IF(K63="No",1,0) | T63: =ROUND((IF(L63="",'Subscriptions'!$T$2,L63)-J63)/30.44,1) | U63: =IF(AND(P63<'Subscriptions'!$T$4,O63<='Subscriptions'!$T$5),1,0)
A64: CUST-0063 | B64: Enterprise | C64: Annual | D64: Retail | E64: 11-50 | F64: 18 | G64: 1505.73 | H64: Organic Search | I64: North America | J64: 45890 | K64: No | N64: 3 | O64: 7 | P64: 61 | Q64: No | R64: =IF(K64="Yes",1,0) | S64: =IF(K64="No",1,0) | T64: =ROUND((IF(L64="",'Subscriptions'!$T$2,L64)-J64)/30.44,1) | U64: =IF(AND(P64<'Subscriptions'!$T$4,O64<='Subscriptions'!$T$5),1,0)
A65: CUST-0064 | B65: Professional | C65: Annual | D65: Retail | E65: 51-200 | F65: 51 | G65: 570.77 | H65: Direct Sales | I65: Asia Pacific | J65: 44836 | K65: No | N65: 1 | O65: 10 | P65: 33 | Q65: No | R65: =IF(K65="Yes",1,0) | S65: =IF(K65="No",1,0) | T65: =ROUND((IF(L65="",'Subscriptions'!$T$2,L65)-J65)/30.44,1) | U65: =IF(AND(P65<'Subscriptions'!$T$4,O65<='Subscriptions'!$T$5),1,0)
A66: CUST-0065 | B66: Starter | C66: Monthly | D66: Manufacturing | E66: 201-500 | F66: 60 | G66: 285.65 | H66: Direct Sales | I66: North America | J66: 44877 | K66: Yes | L66: 44885 | M66: Poor Support | N66: 13 | O66: 3 | P66: 46 | Q66: No | R66: =IF(K66="Yes",1,0) | S66: =IF(K66="No",1,0) | T66: =ROUND((IF(L66="",'Subscriptions'!$T$2,L66)-J66)/30.44,1) | U66: =IF(AND(P66<'Subscriptions'!$T$4,O66<='Subscriptions'!$T$5),1,0)
A67: CUST-0066 | B67: Starter | C67: Annual | D67: Education | E67: 51-200 | F67: 55 | G67: 224.31 | H67: Organic Search | I67: North America | J67: 45471 | K67: Yes | L67: 45494 | M67: Poor Support | N67: 12 | O67: 1 | P67: 12 | Q67: No | R67: =IF(K67="Yes",1,0) | S67: =IF(K67="No",1,0) | T67: =ROUND((IF(L67="",'Subscriptions'!$T$2,L67)-J67)/30.44,1) | U67: =IF(AND(P67<'Subscriptions'!$T$4,O67<='Subscriptions'!$T$5),1,0)
A68: CUST-0067 | B68: Business | C68: Annual | D68: Media | E68: 1-10 | F68: 7 | G68: 321.38 | H68: Paid Ads | I68: North America | J68: 45197 | K68: No | N68: 4 | O68: 8 | P68: 30 | Q68: No | R68: =IF(K68="Yes",1,0) | S68: =IF(K68="No",1,0) | T68: =ROUND((IF(L68="",'Subscriptions'!$T$2,L68)-J68)/30.44,1) | U68: =IF(AND(P68<'Subscriptions'!$T$4,O68<='Subscriptions'!$T$5),1,0)
A69: CUST-0068 | B69: Professional | C69: Annual | D69: Education | E69: 1-10 | F69: 1 | G69: 67.15 | H69: Referral | I69: Asia Pacific | J69: 45993 | K69: No | N69: 7 | O69: 3 | P69: 29 | Q69: No | R69: =IF(K69="Yes",1,0) | S69: =IF(K69="No",1,0) | T69: =ROUND((IF(L69="",'Subscriptions'!$T$2,L69)-J69)/30.44,1) | U69: =IF(AND(P69<'Subscriptions'!$T$4,O69<='Subscriptions'!$T$5),1,0)
A70: CUST-0069 | B70: Starter | C70: Annual | D70: Media | E70: 1-10 | F70: 2 | G70: 28.35 | H70: Organic Search | I70: Europe | J70: 45137 | K70: Yes | L70: 45552 | M70: Missing Features | N70: 1 | O70: 2 | P70: 25 | Q70: No | R70: =IF(K70="Yes",1,0) | S70: =IF(K70="No",1,0) | T70: =ROUND((IF(L70="",'Subscriptions'!$T$2,L70)-J70)/30.44,1) | U70: =IF(AND(P70<'Subscriptions'!$T$4,O70<='Subscriptions'!$T$5),1,0)
A71: CUST-0070 | B71: Business | C71: Monthly | D71: Technology | E71: 51-200 | F71: 64 | G71: 2079.55 | H71: Organic Search | I71: North America | J71: 44798 | K71: Yes | L71: 44800 | M71: No Longer Needed | N71: 3 | O71: 1 | P71: 28 | Q71: No | R71: =IF(K71="Yes",1,0) | S71: =IF(K71="No",1,0) | T71: =ROUND((IF(L71="",'Subscriptions'!$T$2,L71)-J71)/30.44,1) | U71: =IF(AND(P71<'Subscriptions'!$T$4,O71<='Subscriptions'!$T$5),1,0)
A72: CUST-0071 | B72: Enterprise | C72: Monthly | D72: Retail | E72: 201-500 | F72: 58 | G72: 4765.45 | H72: Organic Search | I72: Europe | J72: 44583 | K72: No | N72: 4 | O72: 10 | P72: 42 | Q72: No | R72: =IF(K72="Yes",1,0) | S72: =IF(K72="No",1,0) | T72: =ROUND((IF(L72="",'Subscriptions'!$T$2,L72)-J72)/30.44,1) | U72: =IF(AND(P72<'Subscriptions'!$T$4,O72<='Subscriptions'!$T$5),1,0)
A73: CUST-0072 | B73: Starter | C73: Monthly | D73: Consulting | E73: 51-200 | F73: 31 | G73: 159.5 | H73: Organic Search | I73: North America | J73: 45464 | K73: No | N73: 7 | O73: 10 | P73: 81 | Q73: No | R73: =IF(K73="Yes",1,0) | S73: =IF(K73="No",1,0) | T73: =ROUND((IF(L73="",'Subscriptions'!$T$2,L73)-J73)/30.44,1) | U73: =IF(AND(P73<'Subscriptions'!$T$4,O73<='Subscriptions'!$T$5),1,0)
A74: CUST-0073 | B74: Professional | C74: Monthly | D74: Healthcare | E74: 201-500 | F74: 106 | G74: 1323.25 | H74: Referral | I74: North America | J74: 45797 | K74: No | N74: 7 | O74: 2 | P74: 87 | Q74: Yes | R74: =IF(K74="Yes",1,0) | S74: =IF(K74="No",1,0) | T74: =ROUND((IF(L74="",'Subscriptions'!$T$2,L74)-J74)/30.44,1) | U74: =IF(AND(P74<'Subscriptions'!$T$4,O74<='Subscriptions'!$T$5),1,0)
A75: CUST-0074 | B75: Starter | C75: Monthly | D75: Legal | E75: 51-200 | F75: 42 | G75: 207.35 | H75: Paid Ads | I75: North America | J75: 45274 | K75: Yes | L75: 45629 | M75: Company Closed | N75: 12 | O75: 3 | P75: 10 | Q75: No | R75: =IF(K75="Yes",1,0) | S75: =IF(K75="No",1,0) | T75: =ROUND((IF(L75="",'Subscriptions'!$T$2,L75)-J75)/30.44,1) | U75: =IF(AND(P75<'Subscriptions'!$T$4,O75<='Subscriptions'!$T$5),1,0)
A76: CUST-0075 | B76: Professional | C76: Monthly | D76: Retail | E76: 1-10 | F76: 6 | G76: 138.25 | H76: Paid Ads | I76: North America | J76: 44925 | K76: No | N76: 5 | O76: 1 | P76: 49 | Q76: No | R76: =IF(K76="Yes",1,0) | S76: =IF(K76="No",1,0) | T76: =ROUND((IF(L76="",'Subscriptions'!$T$2,L76)-J76)/30.44,1) | U76: =IF(AND(P76<'Subscriptions'!$T$4,O76<='Subscriptions'!$T$5),1,0)
A77: CUST-0076 | B77: Professional | C77: Annual | D77: Healthcare | E77: 201-500 | F77: 56 | G77: 621.14 | H77: Referral | I77: Europe | J77: 45354 | K77: No | N77: 2 | O77: 5 | P77: 87 | Q77: No | R77: =IF(K77="Yes",1,0) | S77: =IF(K77="No",1,0) | T77: =ROUND((IF(L77="",'Subscriptions'!$T$2,L77)-J77)/30.44,1) | U77: =IF(AND(P77<'Subscriptions'!$T$4,O77<='Subscriptions'!$T$5),1,0)
A78: CUST-0077 | B78: Enterprise | C78: Monthly | D78: Media | E78: 51-200 | F78: 52 | G78: 4316.35 | H78: Partner | I78: Europe | J78: 45047 | K78: No | N78: 4 | O78: 7 | P78: 88 | Q78: No | R78: =IF(K78="Yes",1,0) | S78: =IF(K78="No",1,0) | T78: =ROUND((IF(L78="",'Subscriptions'!$T$2,L78)-J78)/30.44,1) | U78: =IF(AND(P78<'Subscriptions'!$T$4,O78<='Subscriptions'!$T$5),1,0)
A79: CUST-0078 | B79: Starter | C79: Annual | D79: Media | E79: 51-200 | F79: 24 | G79: 109.69 | H79: Partner | I79: Europe | J79: 44978 | K79: Yes | L79: 45909 | M79: Budget Cuts | N79: 2 | O79: 4 | P79: 16 | Q79: No | R79: =IF(K79="Yes",1,0) | S79: =IF(K79="No",1,0) | T79: =ROUND((IF(L79="",'Subscriptions'!$T$2,L79)-J79)/30.44,1) | U79: =IF(AND(P79<'Subscriptions'!$T$4,O79<='Subscriptions'!$T$5),1,0)
A80: CUST-0079 | B80: Business | C80: Monthly | D80: Healthcare | E80: 51-200 | F80: 40 | G80: 1363.15 | H80: Social Media | I80: North America | J80: 45297 | K80: No | N80: 0 | O80: 4 | P80: 29 | Q80: No | R80: =IF(K80="Yes",1,0) | S80: =IF(K80="No",1,0) | T80: =ROUND((IF(L80="",'Subscriptions'!$T$2,L80)-J80)/30.44,1) | U80: =IF(AND(P80<'Subscriptions'!$T$4,O80<='Subscriptions'!$T$5),1,0)
A81: CUST-0080 | B81: Starter | C81: Monthly | D81: Healthcare | E81: 11-50 | F81: 5 | G81: 46.4 | H81: Organic Search | I81: Asia Pacific | J81: 45721 | K81: Yes | L81: 45753 | M81: No Longer Needed | N81: 0 | O81: 6 | P81: 20 | Q81: No | R81: =IF(K81="Yes",1,0) | S81: =IF(K81="No",1,0) | T81: =ROUND((IF(L81="",'Subscriptions'!$T$2,L81)-J81)/30.44,1) | U81: =IF(AND(P81<'Subscriptions'!$T$4,O81<='Subscriptions'!$T$5),1,0)
A82: CUST-0081 | B82: Business | C82: Annual | D82: Finance | E82: 11-50 | F82: 24 | G82: 752.72 | H82: Organic Search | I82: Asia Pacific | J82: 45308 | K82: No | N82: 2 | O82: 6 | P82: 86 | Q82: No | R82: =IF(K82="Yes",1,0) | S82: =IF(K82="No",1,0) | T82: =ROUND((IF(L82="",'Subscriptions'!$T$2,L82)-J82)/30.44,1) | U82: =IF(AND(P82<'Subscriptions'!$T$4,O82<='Subscriptions'!$T$5),1,0)
A83: CUST-0082 | B83: Starter | C83: Annual | D83: Technology | E83: 1-10 | F83: 1 | G83: 24.65 | H83: Social Media | I83: Europe | J83: 45462 | K83: Yes | L83: 45812 | M83: Budget Cuts | N83: 14 | O83: 2 | P83: 22 | Q83: No | R83: =IF(K83="Yes",1,0) | S83: =IF(K83="No",1,0) | T83: =ROUND((IF(L83="",'Subscriptions'!$T$2,L83)-J83)/30.44,1) | U83: =IF(AND(P83<'Subscriptions'!$T$4,O83<='Subscriptions'!$T$5),1,0)
A84: CUST-0083 | B84: Professional | C84: Monthly | D84: Education | E84: 1-10 | F84: 5 | G84: 126.4 | H84: Paid Ads | I84: Asia Pacific | J84: 45912 | K84: No | N84: 6 | O84: 9 | P84: 56 | Q84: No | R84: =IF(K84="Yes",1,0) | S84: =IF(K84="No",1,0) | T84: =ROUND((IF(L84="",'Subscriptions'!$T$2,L84)-J84)/30.44,1) | U84: =IF(AND(P84<'Subscriptions'!$T$4,O84<='Subscriptions'!$T$5),1,0)
A85: CUST-0084 | B85: Business | C85: Monthly | D85: Real Estate | E85: 201-500 | F85: 71 | G85: 2288.5 | H85: Referral | I85: Europe | J85: 44947 | K85: Yes | L85: 45308 | M85: Missing Features | N85: 6 | O85: 5 | P85: 29 | Q85: No | R85: =IF(K85="Yes",1,0) | S85: =IF(K85="No",1,0) | T85: =ROUND((IF(L85="",'Subscriptions'!$T$2,L85)-J85)/30.44,1) | U85: =IF(AND(P85<'Subscriptions'!$T$4,O85<='Subscriptions'!$T$5),1,0)
A86: CUST-0085 | B86: Starter | C86: Monthly | D86: Real Estate | E86: 11-50 | F86: 21 | G86: 116 | H86: Partner | I86: Latin America | J86: 45661 | K86: Yes | L86: 45730 | M86: Company Closed | N86: 13 | O86: 2 | P86: 42 | Q86: No | R86: =IF(K86="Yes",1,0) | S86: =IF(K86="No",1,0) | T86: =ROUND((IF(L86="",'Subscriptions'!$T$2,L86)-J86)/30.44,1) | U86: =IF(AND(P86<'Subscriptions'!$T$4,O86<='Subscriptions'!$T$5),1,0)
A87: CUST-0086 | B87: Business | C87: Monthly | D87: Technology | E87: 11-50 | F87: 27 | G87: 975.1 | H87: Partner | I87: Europe | J87: 45479 | K87: No | N87: 9 | O87: 7 | P87: 35 | Q87: No | R87: =IF(K87="Yes",1,0) | S87: =IF(K87="No",1,0) | T87: =ROUND((IF(L87="",'Subscriptions'!$T$2,L87)-J87)/30.44,1) | U87: =IF(AND(P87<'Subscriptions'!$T$4,O87<='Subscriptions'!$T$5),1,0)
A88: CUST-0087 | B88: Professional | C88: Annual | D88: Education | E88: 51-200 | F88: 17 | G88: 228.31 | H88: Direct Sales | I88: Europe | J88: 45421 | K88: No | N88: 2 | O88: 4 | P88: 88 | Q88: No | R88: =IF(K88="Yes",1,0) | S88: =IF(K88="No",1,0) | T88: =ROUND((IF(L88="",'Subscriptions'!$T$2,L88)-J88)/30.44,1) | U88: =IF(AND(P88<'Subscriptions'!$T$4,O88<='Subscriptions'!$T$5),1,0)
A89: CUST-0088 | B89: Starter | C89: Monthly | D89: Consulting | E89: 51-200 | F89: 76 | G89: 355.25 | H89: Referral | I89: Asia Pacific | J89: 45641 | K89: Yes | L89: 45806 | M89: Budget Cuts | N89: 7 | O89: 3 | P89: 20 | Q89: No | R89: =IF(K89="Yes",1,0) | S89: =IF(K89="No",1,0) | T89: =ROUND((IF(L89="",'Subscriptions'!$T$2,L89)-J89)/30.44,1) | U89: =IF(AND(P89<'Subscriptions'!$T$4,O89<='Subscriptions'!$T$5),1,0)
A90: CUST-0089 | B90: Professional | C90: Annual | D90: Healthcare | E90: 201-500 | F90: 75 | G90: 812.51 | H90: Organic Search | I90: Asia Pacific | J90: 44886 | K90: Yes | L90: 45200 | M90: Poor Support | N90: 12 | O90: 6 | P90: 20 | Q90: No | R90: =IF(K90="Yes",1,0) | S90: =IF(K90="No",1,0) | T90: =ROUND((IF(L90="",'Subscriptions'!$T$2,L90)-J90)/30.44,1) | U90: =IF(AND(P90<'Subscriptions'!$T$4,O90<='Subscriptions'!$T$5),1,0)
A91: CUST-0090 | B91: Business | C91: Annual | D91: Healthcare | E91: 51-200 | F91: 67 | G91: 1843.73 | H91: Paid Ads | I91: Europe | J91: 44648 | K91: Yes | L91: 44885 | M91: Switched Competitor | N91: 7 | O91: 1 | P91: 36 | Q91: No | R91: =IF(K91="Yes",1,0) | S91: =IF(K91="No",1,0) | T91: =ROUND((IF(L91="",'Subscriptions'!$T$2,L91)-J91)/30.44,1) | U91: =IF(AND(P91<'Subscriptions'!$T$4,O91<='Subscriptions'!$T$5),1,0)
A92: CUST-0091 | B92: Enterprise | C92: Annual | D92: Media | E92: 11-50 | F92: 20 | G92: 1632.98 | H92: Referral | I92: North America | J92: 45596 | K92: Yes | L92: 45710 | M92: Company Closed | N92: 13 | O92: 2 | P92: 42 | Q92: No | R92: =IF(K92="Yes",1,0) | S92: =IF(K92="No",1,0) | T92: =ROUND((IF(L92="",'Subscriptions'!$T$2,L92)-J92)/30.44,1) | U92: =IF(AND(P92<'Subscriptions'!$T$4,O92<='Subscriptions'!$T$5),1,0)
A93: CUST-0092 | B93: Starter | C93: Monthly | D93: Consulting | E93: 1-10 | F93: 5 | G93: 46.4 | H93: Partner | I93: Asia Pacific | J93: 45732 | K93: No | N93: 7 | O93: 7 | P93: 41 | Q93: No | R93: =IF(K93="Yes",1,0) | S93: =IF(K93="No",1,0) | T93: =ROUND((IF(L93="",'Subscriptions'!$T$2,L93)-J93)/30.44,1) | U93: =IF(AND(P93<'Subscriptions'!$T$4,O93<='Subscriptions'!$T$5),1,0)
A94: CUST-0093 | B94: Starter | C94: Monthly | D94: Manufacturing | E94: 1-10 | F94: 7 | G94: 55.1 | H94: Direct Sales | I94: North America | J94: 45960 | K94: No | N94: 2 | O94: 10 | P94: 63 | Q94: No | R94: =IF(K94="Yes",1,0) | S94: =IF(K94="No",1,0) | T94: =ROUND((IF(L94="",'Subscriptions'!$T$2,L94)-J94)/30.44,1) | U94: =IF(AND(P94<'Subscriptions'!$T$4,O94<='Subscriptions'!$T$5),1,0)
A95: CUST-0094 | B95: Business | C95: Monthly | D95: Education | E95: 500+ | F95: 234 | G95: 7154.05 | H95: Partner | I95: North America | J95: 44771 | K95: Yes | L95: 45930 | M95: Poor Support | N95: 4 | O95: 6 | P95: 14 | Q95: No | R95: =IF(K95="Yes",1,0) | S95: =IF(K95="No",1,0) | T95: =ROUND((IF(L95="",'Subscriptions'!$T$2,L95)-J95)/30.44,1) | U95: =IF(AND(P95<'Subscriptions'!$T$4,O95<='Subscriptions'!$T$5),1,0)
A96: CUST-0095 | B96: Professional | C96: Monthly | D96: Finance | E96: 11-50 | F96: 14 | G96: 233.05 | H96: Paid Ads | I96: North America | J96: 44859 | K96: Yes | L96: 45025 | M96: Budget Cuts | N96: 5 | O96: 6 | P96: 11 | Q96: No | R96: =IF(K96="Yes",1,0) | S96: =IF(K96="No",1,0) | T96: =ROUND((IF(L96="",'Subscriptions'!$T$2,L96)-J96)/30.44,1) | U96: =IF(AND(P96<'Subscriptions'!$T$4,O96<='Subscriptions'!$T$5),1,0)
A97: CUST-0096 | B97: Starter | C97: Monthly | D97: Legal | E97: 11-50 | F97: 15 | G97: 89.9 | H97: Direct Sales | I97: North America | J97: 45169 | K97: Yes | L97: 45195 | M97: Price Too High | N97: 12 | O97: 1 | P97: 12 | Q97: No | R97: =IF(K97="Yes",1,0) | S97: =IF(K97="No",1,0) | T97: =ROUND((IF(L97="",'Subscriptions'!$T$2,L97)-J97)/30.44,1) | U97: =IF(AND(P97<'Subscriptions'!$T$4,O97<='Subscriptions'!$T$5),1,0)
A98: CUST-0097 | B98: Enterprise | C98: Monthly | D98: Education | E98: 51-200 | F98: 31 | G98: 2744.5 | H98: Organic Search | I98: North America | J98: 45215 | K98: No | N98: 1 | O98: 1 | P98: 22 | Q98: No | R98: =IF(K98="Yes",1,0) | S98: =IF(K98="No",1,0) | T98: =ROUND((IF(L98="",'Subscriptions'!$T$2,L98)-J98)/30.44,1) | U98: =IF(AND(P98<'Subscriptions'!$T$4,O98<='Subscriptions'!$T$5),1,0)
A99: CUST-0098 | B99: Professional | C99: Annual | D99: Consulting | E99: 1-10 | F99: 8 | G99: 137.66 | H99: Organic Search | I99: North America | J99: 45989 | K99: Yes | L99: 46005 | M99: Company Closed | N99: 10 | O99: 6 | P99: 43 | Q99: No | R99: =IF(K99="Yes",1,0) | S99: =IF(K99="No",1,0) | T99: =ROUND((IF(L99="",'Subscriptions'!$T$2,L99)-J99)/30.44,1) | U99: =IF(AND(P99<'Subscriptions'!$T$4,O99<='Subscriptions'!$T$5),1,0)
A100: CUST-0099 | B100: Enterprise | C100: Monthly | D100: Manufacturing | E100: 11-50 | F100: 6 | G100: 873.25 | H100: Organic Search | I100: Asia Pacific | J100: 44792 | K100: No | N100: 3 | O100: 4 | P100: 70 | Q100: No | R100: =IF(K100="Yes",1,0) | S100: =IF(K100="No",1,0) | T100: =ROUND((IF(L100="",'Subscriptions'!$T$2,L100)-J100)/30.44,1) | U100: =IF(AND(P100<'Subscriptions'!$T$4,O100<='Subscriptions'!$T$5),1,0)
...

Sheet Monthly Revenue
A1: month | B1: total_active_customers | C1: new_customers | D1: churned_customers | E1: monthly_churn_rate_pct | F1: total_mrr | G1: avg_revenue_per_customer | H1: customer_acquisition_cost
A2: 2022-01 | B2: 0 | C2: 5 | D2: 0 | E2: 0 | F2: 0 | G2: 0 | H2: 164.92
A3: 2022-02 | B3: 5 | C3: 10 | D3: 1 | E3: 20 | F3: 7333.07 | G3: 1466.61 | H3: 189.21
A4: 2022-03 | B4: 14 | C4: 13 | D4: 0 | E4: 0 | F4: 12301.16 | G4: 878.65 | H4: 139.49
A5: 2022-04 | B5: 28 | C5: 11 | D5: 3 | E5: 10.71 | F5: 24798.76 | G5: 885.67 | H5: 259.09
A6: 2022-05 | B6: 35 | C6: 11 | D6: 1 | E6: 2.86 | F6: 29091.88 | G6: 831.2 | H6: 152.96
A7: 2022-06 | B7: 46 | C7: 10 | D7: 2 | E7: 4.35 | F7: 38919.93 | G7: 846.09 | H7: 248.89
A8: 2022-07 | B8: 53 | C8: 8 | D8: 6 | E8: 11.32 | F8: 45097.72 | G8: 850.9 | H8: 275.08
A9: 2022-08 | B9: 57 | C9: 18 | D9: 6 | E9: 10.53 | F9: 54140.41 | G9: 949.83 | H9: 193.48
A10: 2022-09 | B10: 67 | C10: 13 | D10: 5 | E10: 7.46 | F10: 65198 | G10: 973.1 | H10: 216
A11: 2022-10 | B11: 76 | C11: 16 | D11: 5 | E11: 6.58 | F11: 86824.16 | G11: 1142.42 | H11: 246.32
A12: 2022-11 | B12: 87 | C12: 14 | D12: 5 | E12: 5.75 | F12: 93168.11 | G12: 1070.9 | H12: 130.12
A13: 2022-12 | B13: 95 | C13: 14 | D13: 2 | E13: 2.11 | F13: 96100.66 | G13: 1011.59 | H13: 160.94
... A49: 2025-12 | B49: 281 | C49: 11 | D49: 4 | E49: 1.42 | F49: 292628.61 | G49: 1041.38 | H49: 151.47

Sheet Churn Summary
A1: Churn Summary
A2: Churn rate by plan, billing cycle, acquisition channel, and company size. Every cell below is a live COUNTIFS/SUMIFS formula against the Subscriptions tab.
A4: Churn Rate by Plan
A5: Plan | B5: Customers | C5: Churned | D5: Churn Rate | E5: Avg MRR
A6: Starter | B6: =COUNTIF(Subscriptions!$B$2:$B$601,A6) | C6: =SUMIFS(Subscriptions!$R$2:$R$601,Subscriptions!$B$2:$B$601,A6) | D6: =C6/B6 | E6: =AVERAGEIFS(Subscriptions!$G$2:$G$601,Subscriptions!$B$2:$B$601,A6)
A7: Professional | B7: =COUNTIF(Subscriptions!$B$2:$B$601,A7) | C7: =SUMIFS(Subscriptions!$R$2:$R$601,Subscriptions!$B$2:$B$601,A7) | D7: =C7/B7 | E7: =AVERAGEIFS(Subscriptions!$G$2:$G$601,Subscriptions!$B$2:$B$601,A7)
A8: Business | B8: =COUNTIF(Subscriptions!$B$2:$B$601,A8) | C8: =SUMIFS(Subscriptions!$R$2:$R$601,Subscriptions!$B$2:$B$601,A8) | D8: =C8/B8 | E8: =AVERAGEIFS(Subscriptions!$G$2:$G$601,Subscriptions!$B$2:$B$601,A8)
A9: Enterprise | B9: =COUNTIF(Subscriptions!$B$2:$B$601,A9) | C9: =SUMIFS(Subscriptions!$R$2:$R$601,Subscriptions!$B$2:$B$601,A9) | D9: =C9/B9 | E9: =AVERAGEIFS(Subscriptions!$G$2:$G$601,Subscriptions!$B$2:$B$601,A9)
A11: Churn Rate by Billing Cycle
A12: Billing Cycle | B12: Customers | C12: Churned | D12: Churn Rate
A13: Monthly | B13: =COUNTIF(Subscriptions!$C$2:$C$601,A13) | C13: =SUMIFS(Subscriptions!$R$2:$R$601,Subscriptions!$C$2:$C$601,A13) | D13: =C13/B13
A14: Annual | B14: =COUNTIF(Subscriptions!$C$2:$C$601,A14) | C14: =SUMIFS(Subscriptions!$R$2:$R$601,Subscriptions!$C$2:$C$601,A14) | D14: =C14/B14
A16: Churn Rate by Plan x Billing Cycle
A17: Plan | B17: Monthly Churn Rate | C17: Annual Churn Rate
A18: Starter | B18: =SUMIFS(Subscriptions!$R$2:$R$601,Subscriptions!$B$2:$B$601,A18,Subscriptions!$C$2:$C$601,"Monthly")/COUNTIFS(Subscriptions!$B$2:$B$601,A18,Subscriptions!$C$2:$C$601,"Monthly") | C18: =SUMIFS(Subscriptions!$R$2:$R$601,Subscriptions!$B$2:$B$601,A18,Subscriptions!$C$2:$C$601,"Annual")/COUNTIFS(Subscriptions!$B$2:$B$601,A18,Subscriptions!$C$2:$C$601,"Annual")
A19: Professional | B19: =SUMIFS(Subscriptions!$R$2:$R$601,Subscriptions!$B$2:$B$601,A19,Subscriptions!$C$2:$C$601,"Monthly")/COUNTIFS(Subscriptions!$B$2:$B$601,A19,Subscriptions!$C$2:$C$601,"Monthly") | C19: =SUMIFS(Subscriptions!$R$2:$R$601,Subscriptions!$B$2:$B$601,A19,Subscriptions!$C$2:$C$601,"Annual")/COUNTIFS(Subscriptions!$B$2:$B$601,A19,Subscriptions!$C$2:$C$601,"Annual")
A20: Business | B20: =SUMIFS(Subscriptions!$R$2:$R$601,Subscriptions!$B$2:$B$601,A20,Subscriptions!$C$2:$C$601,"Monthly")/COUNTIFS(Subscriptions!$B$2:$B$601,A20,Subscriptions!$C$2:$C$601,"Monthly") | C20: =SUMIFS(Subscriptions!$R$2:$R$601,Subscriptions!$B$2:$B$601,A20,Subscriptions!$C$2:$C$601,"Annual")/COUNTIFS(Subscriptions!$B$2:$B$601,A20,Subscriptions!$C$2:$C$601,"Annual")
A21: Enterprise | B21: =SUMIFS(Subscriptions!$R$2:$R$601,Subscriptions!$B$2:$B$601,A21,Subscriptions!$C$2:$C$601,"Monthly")/COUNTIFS(Subscriptions!$B$2:$B$601,A21,Subscriptions!$C$2:$C$601,"Monthly") | C21: =SUMIFS(Subscriptions!$R$2:$R$601,Subscriptions!$B$2:$B$601,A21,Subscriptions!$C$2:$C$601,"Annual")/COUNTIFS(Subscriptions!$B$2:$B$601,A21,Subscriptions!$C$2:$C$601,"Annual")
A23: Churn Rate by Acquisition Channel
A24: Channel | B24: Customers | C24: Churned | D24: Churn Rate
A25: Referral | B25: =COUNTIF(Subscriptions!$H$2:$H$601,A25) | C25: =SUMIFS(Subscriptions!$R$2:$R$601,Subscriptions!$H$2:$H$601,A25) | D25: =C25/B25
A26: Partner | B26: =COUNTIF(Subscriptions!$H$2:$H$601,A26) | C26: =SUMIFS(Subscriptions!$R$2:$R$601,Subscriptions!$H$2:$H$601,A26) | D26: =C26/B26
A27: Social Media | B27: =COUNTIF(Subscriptions!$H$2:$H$601,A27) | C27: =SUMIFS(Subscriptions!$R$2:$R$601,Subscriptions!$H$2:$H$601,A27) | D27: =C27/B27
A28: Paid Ads | B28: =COUNTIF(Subscriptions!$H$2:$H$601,A28) | C28: =SUMIFS(Subscriptions!$R$2:$R$601,Subscriptions!$H$2:$H$601,A28) | D28: =C28/B28
A29: Organic Search | B29: =COUNTIF(Subscriptions!$H$2:$H$601,A29) | C29: =SUMIFS(Subscriptions!$R$2:$R$601,Subscriptions!$H$2:$H$601,A29) | D29: =C29/B29
A30: Direct Sales | B30: =COUNTIF(Subscriptions!$H$2:$H$601,A30) | C30: =SUMIFS(Subscriptions!$R$2:$R$601,Subscriptions!$H$2:$H$601,A30) | D30: =C30/B30
A32: Churn Rate by Company Size
A33: Company Size | B33: Customers | C33: Churned | D33: Churn Rate
A34: 1-10 | B34: =COUNTIF(Subscriptions!$E$2:$E$601,A34) | C34: =SUMIFS(Subscriptions!$R$2:$R$601,Subscriptions!$E$2:$E$601,A34) | D34: =C34/B34
A35: 11-50 | B35: =COUNTIF(Subscriptions!$E$2:$E$601,A35) | C35: =SUMIFS(Subscriptions!$R$2:$R$601,Subscriptions!$E$2:$E$601,A35) | D35: =C35/B35
A36: 51-200 | B36: =COUNTIF(Subscriptions!$E$2:$E$601,A36) | C36: =SUMIFS(Subscriptions!$R$2:$R$601,Subscriptions!$E$2:$E$601,A36) | D36: =C36/B36
A37: 201-500 | B37: =COUNTIF(Subscriptions!$E$2:$E$601,A37) | C37: =SUMIFS(Subscriptions!$R$2:$R$601,Subscriptions!$E$2:$E$601,A37) | D37: =C37/B37
A38: 500+ | B38: =COUNTIF(Subscriptions!$E$2:$E$601,A38) | C38: =SUMIFS(Subscriptions!$R$2:$R$601,Subscriptions!$E$2:$E$601,A38) | D38: =C38/B38

Sheet Churn Reasons
A1: Churn Reasons
A2: Top reasons customers churn, overall and by plan. COUNTIFS formulas against the Subscriptions tab.
A4: Overall Churn Reasons
A5: Reason | B5: Churned Customers | C5: % of All Churn
A6: Budget Cuts | B6: =COUNTIF(Subscriptions!$M$2:$M$601,A6) | C6: =B6/SUM(Subscriptions!$R$2:$R$601)
A7: Price Too High | B7: =COUNTIF(Subscriptions!$M$2:$M$601,A7) | C7: =B7/SUM(Subscriptions!$R$2:$R$601)
A8: Company Closed | B8: =COUNTIF(Subscriptions!$M$2:$M$601,A8) | C8: =B8/SUM(Subscriptions!$R$2:$R$601)
A9: Poor Support | B9: =COUNTIF(Subscriptions!$M$2:$M$601,A9) | C9: =B9/SUM(Subscriptions!$R$2:$R$601)
A10: No Longer Needed | B10: =COUNTIF(Subscriptions!$M$2:$M$601,A10) | C10: =B10/SUM(Subscriptions!$R$2:$R$601)
A11: Missing Features | B11: =COUNTIF(Subscriptions!$M$2:$M$601,A11) | C11: =B11/SUM(Subscriptions!$R$2:$R$601)
A12: Switched Competitor | B12: =COUNTIF(Subscriptions!$M$2:$M$601,A12) | C12: =B12/SUM(Subscriptions!$R$2:$R$601)
A14: Reason Breakdown by Plan (count of churned customers)
A15: Plan | B15: Budget Cuts | C15: Price Too High | D15: Company Closed | E15: Poor Support | F15: No Longer Needed | G15: Missing Features | H15: Switched Competitor
A16: Starter | B16: =COUNTIFS(Subscriptions!$B$2:$B$601,$A16,Subscriptions!$M$2:$M$601,B$15) | C16: =COUNTIFS(Subscriptions!$B$2:$B$601,$A16,Subscriptions!$M$2:$M$601,C$15) | D16: =COUNTIFS(Subscriptions!$B$2:$B$601,$A16,Subscriptions!$M$2:$M$601,D$15) | E16: =COUNTIFS(Subscriptions!$B$2:$B$601,$A16,Subscriptions!$M$2:$M$601,E$15) | F16: =COUNTIFS(Subscriptions!$B$2:$B$601,$A16,Subscriptions!$M$2:$M$601,F$15) | G16: =COUNTIFS(Subscriptions!$B$2:$B$601,$A16,Subscriptions!$M$2:$M$601,G$15) | H16: =COUNTIFS(Subscriptions!$B$2:$B$601,$A16,Subscriptions!$M$2:$M$601,H$15)
A17: Professional | B17: =COUNTIFS(Subscriptions!$B$2:$B$601,$A17,Subscriptions!$M$2:$M$601,B$15) | C17: =COUNTIFS(Subscriptions!$B$2:$B$601,$A17,Subscriptions!$M$2:$M$601,C$15) | D17: =COUNTIFS(Subscriptions!$B$2:$B$601,$A17,Subscriptions!$M$2:$M$601,D$15) | E17: =COUNTIFS(Subscriptions!$B$2:$B$601,$A17,Subscriptions!$M$2:$M$601,E$15) | F17: =COUNTIFS(Subscriptions!$B$2:$B$601,$A17,Subscriptions!$M$2:$M$601,F$15) | G17: =COUNTIFS(Subscriptions!$B$2:$B$601,$A17,Subscriptions!$M$2:$M$601,G$15) | H17: =COUNTIFS(Subscriptions!$B$2:$B$601,$A17,Subscriptions!$M$2:$M$601,H$15)
A18: Business | B18: =COUNTIFS(Subscriptions!$B$2:$B$601,$A18,Subscriptions!$M$2:$M$601,B$15) | C18: =COUNTIFS(Subscriptions!$B$2:$B$601,$A18,Subscriptions!$M$2:$M$601,C$15) | D18: =COUNTIFS(Subscriptions!$B$2:$B$601,$A18,Subscriptions!$M$2:$M$601,D$15) | E18: =COUNTIFS(Subscriptions!$B$2:$B$601,$A18,Subscriptions!$M$2:$M$601,E$15) | F18: =COUNTIFS(Subscriptions!$B$2:$B$601,$A18,Subscriptions!$M$2:$M$601,F$15) | G18: =COUNTIFS(Subscriptions!$B$2:$B$601,$A18,Subscriptions!$M$2:$M$601,G$15) | H18: =COUNTIFS(Subscriptions!$B$2:$B$601,$A18,Subscriptions!$M$2:$M$601,H$15)
A19: Enterprise | B19: =COUNTIFS(Subscriptions!$B$2:$B$601,$A19,Subscriptions!$M$2:$M$601,B$15) | C19: =COUNTIFS(Subscriptions!$B$2:$B$601,$A19,Subscriptions!$M$2:$M$601,C$15) | D19: =COUNTIFS(Subscriptions!$B$2:$B$601,$A19,Subscriptions!$M$2:$M$601,D$15) | E19: =COUNTIFS(Subscriptions!$B$2:$B$601,$A19,Subscriptions!$M$2:$M$601,E$15) | F19: =COUNTIFS(Subscriptions!$B$2:$B$601,$A19,Subscriptions!$M$2:$M$601,F$15) | G19: =COUNTIFS(Subscriptions!$B$2:$B$601,$A19,Subscriptions!$M$2:$M$601,G$15) | H19: =COUNTIFS(Subscriptions!$B$2:$B$601,$A19,Subscriptions!$M$2:$M$601,H$15)
A21: Top Reason by Plan
A22: Plan | B22: Top Reason | C22: Count
A23: Starter | B23: =INDEX($B$15:$H$15,MATCH(MAX(B16:H16),B16:H16,0)) | C23: =MAX(B16:H16)
A24: Professional | B24: =INDEX($B$15:$H$15,MATCH(MAX(B17:H17),B17:H17,0)) | C24: =MAX(B17:H17)
A25: Business | B25: =INDEX($B$15:$H$15,MATCH(MAX(B18:H18),B18:H18,0)) | C25: =MAX(B18:H18)
A26: Enterprise | B26: =INDEX($B$15:$H$15,MATCH(MAX(B19:H19),B19:H19,0)) | C26: =MAX(B19:H19)

Sheet Unit Economics
A1: Unit Economics
A2: Average CLV by plan vs. blended CAC. CAC is a single company-wide figure -- the source data doesn't split acquisition cost by plan, so the same blended CAC is compared against every plan's CLV (see the note below).
A4: Blended CAC (weighted by customers acquired per month)
A5: Blended CAC | B5: =SUMPRODUCT('Monthly Revenue'!$C$2:$C$49,'Monthly Revenue'!$H$2:$H$49)/SUM('Monthly Revenue'!$C$2:$C$49)
A7: CLV by Plan
A8: Plan | B8: Avg MRR | C8: Avg Lifespan (months) | D8: Avg CLV | E8: Blended CAC | F8: CLV : CAC Ratio
A9: Starter | B9: =AVERAGEIF(Subscriptions!$B$2:$B$601,A9,Subscriptions!$G$2:$G$601) | C9: =AVERAGEIF(Subscriptions!$B$2:$B$601,A9,Subscriptions!$T$2:$T$601) | D9: =B9*C9 | E9: =$B$5 | F9: =D9/E9
A10: Professional | B10: =AVERAGEIF(Subscriptions!$B$2:$B$601,A10,Subscriptions!$G$2:$G$601) | C10: =AVERAGEIF(Subscriptions!$B$2:$B$601,A10,Subscriptions!$T$2:$T$601) | D10: =B10*C10 | E10: =$B$5 | F10: =D10/E10
A11: Business | B11: =AVERAGEIF(Subscriptions!$B$2:$B$601,A11,Subscriptions!$G$2:$G$601) | C11: =AVERAGEIF(Subscriptions!$B$2:$B$601,A11,Subscriptions!$T$2:$T$601) | D11: =B11*C11 | E11: =$B$5 | F11: =D11/E11
A12: Enterprise | B12: =AVERAGEIF(Subscriptions!$B$2:$B$601,A12,Subscriptions!$G$2:$G$601) | C12: =AVERAGEIF(Subscriptions!$B$2:$B$601,A12,Subscriptions!$T$2:$T$601) | D12: =B12*C12 | E12: =$B$5 | F12: =D12/E12
A14: Note: a ratio below 3x is the usual red flag in SaaS unit economics; below 1x means the plan loses money on acquisition alone. All four plans clear that bar comfortably here because CAC is low relative to plan MRR -- Starter's concern is its short average lifespan and low CLV in absolute dollars, not CAC efficiency.

Sheet At-Risk Customers
A1: At-Risk Customers
A2: Relationship between feature usage, NPS, and churn, and the current at-risk customer list. Threshold cells (yellow) live on the Subscriptions tab and drive the Is At Risk column used everywhere below.
A4: Churned vs. Active — average usage, NPS, support tickets
A5: Status | B5: Avg Feature Usage % | C5: Avg NPS | D5: Avg Support Tickets (12mo)
A6: Active | B6: =AVERAGEIF(Subscriptions!$K$2:$K$601,"No",Subscriptions!$P$2:$P$601) | C6: =AVERAGEIF(Subscriptions!$K$2:$K$601,"No",Subscriptions!$O$2:$O$601) | D6: =AVERAGEIF(Subscriptions!$K$2:$K$601,"No",Subscriptions!$N$2:$N$601)
A7: Churned | B7: =AVERAGEIF(Subscriptions!$K$2:$K$601,"Yes",Subscriptions!$P$2:$P$601) | C7: =AVERAGEIF(Subscriptions!$K$2:$K$601,"Yes",Subscriptions!$O$2:$O$601) | D7: =AVERAGEIF(Subscriptions!$K$2:$K$601,"Yes",Subscriptions!$N$2:$N$601)
A9: Current At-Risk Base (active customers only)
A10: Metric | B10: Value
A11: Active customers | B11: =SUM(Subscriptions!$S$2:$S$601)
A12: At-risk active customers | B12: =SUMIFS(Subscriptions!$U$2:$U$601,Subscriptions!$S$2:$S$601,1)
A13: % of active base at risk | B13: =B12/B11
A14: At-risk MRR | B14: =SUMIFS(Subscriptions!$G$2:$G$601,Subscriptions!$U$2:$U$601,1,Subscriptions!$S$2:$S$601,1)
A16: At-Risk Customers by Plan
A17: Plan | B17: Active Customers | C17: At-Risk Customers | D17: % At Risk
A18: Starter | B18: =COUNTIFS(Subscriptions!$B$2:$B$601,A18,Subscriptions!$S$2:$S$601,1) | C18: =SUMIFS(Subscriptions!$U$2:$U$601,Subscriptions!$B$2:$B$601,A18,Subscriptions!$S$2:$S$601,1) | D18: =C18/B18
A19: Professional | B19: =COUNTIFS(Subscriptions!$B$2:$B$601,A19,Subscriptions!$S$2:$S$601,1) | C19: =SUMIFS(Subscriptions!$U$2:$U$601,Subscriptions!$B$2:$B$601,A19,Subscriptions!$S$2:$S$601,1) | D19: =C19/B19
A20: Business | B20: =COUNTIFS(Subscriptions!$B$2:$B$601,A20,Subscriptions!$S$2:$S$601,1) | C20: =SUMIFS(Subscriptions!$U$2:$U$601,Subscriptions!$B$2:$B$601,A20,Subscriptions!$S$2:$S$601,1) | D20: =C20/B20
A21: Enterprise | B21: =COUNTIFS(Subscriptions!$B$2:$B$601,A21,Subscriptions!$S$2:$S$601,1) | C21: =SUMIFS(Subscriptions!$U$2:$U$601,Subscriptions!$B$2:$B$601,A21,Subscriptions!$S$2:$S$601,1) | D21: =C21/B21
A24: Current At-Risk Customer List (for CS outreach)
A25: Filtered from Subscriptions: Is Active = 1 AND Is At Risk = 1, sorted by MRR descending. Re-derive this list (Data > Filter on the Subscriptions tab) after refreshing the raw data -- it's a snapshot, not a live spill formula.
A26: Customer ID | B26: Plan | C26: Company Size | D26: MRR | E26: NPS | F26: Feature Usage % | G26: Acquisition Channel
A27: CUST-0211 | B27: Enterprise | C27: 201-500 | D27: 3414.41 | E27: 2 | F27: 23 | G27: Paid Ads
A28: CUST-0097 | B28: Enterprise | C28: 51-200 | D28: 2744.5 | E28: 1 | F28: 22 | G28: Organic Search
A29: CUST-0530 | B29: Enterprise | C29: 11-50 | D29: 2744.5 | E29: 3 | F29: 15 | G29: Partner
A30: CUST-0458 | B30: Business | C30: 201-500 | D30: 1995.97 | E30: 1 | F30: 15 | G30: Referral
A31: CUST-0516 | B31: Business | C31: 51-200 | D31: 1422.85 | E31: 2 | F31: 17 | G31: Partner
A32: CUST-0079 | B32: Business | C32: 51-200 | D32: 1363.15 | E32: 4 | F32: 29 | G32: Social Media
A33: CUST-0570 | B33: Business | C33: 11-50 | D33: 727.34 | E33: 5 | F33: 19 | G33: Organic Search
A34: CUST-0100 | B34: Business | C34: 11-50 | D34: 676.6 | E34: 4 | F34: 17 | G34: Paid Ads
A35: CUST-0544 | B35: Business | C35: 11-50 | D35: 549.74 | E35: 3 | F35: 25 | G35: Referral
A36: CUST-0405 | B36: Business | C36: 11-50 | D36: 378.1 | E36: 1 | F36: 29 | G36: Paid Ads
A37: CUST-0591 | B37: Business | C37: 11-50 | D37: 348.25 | E37: 2 | F37: 27 | G37: Organic Search
A38: CUST-0313 | B38: Starter | C38: 51-200 | D38: 346.55 | E38: 4 | F38: 18 | G38: Organic Search
... A49: CUST-0360 | B49: Starter | C49: 1-10 | D49: 28.35 | E49: 6 | F49: 20 | G49: Social Media
